{
    "request": {
        "command": "series",
        "series_id": "ELEC.CONS_TOT_BTU.NG-CO-99.Q"
    },
    "series": [
        {
            "series_id": "ELEC.CONS_TOT_BTU.NG-CO-99.Q",
            "name": "Total consumption (Btu) : natural gas : Colorado : all sectors : quarterly",
            "units": "million MMBtu",
            "f": "Q",
            "description": "Natural Gas; All sectors; ",
            "copyright": "None",
            "source": "EIA, U.S. Energy Information Administration",
            "iso3166": "USA-CO",
            "geography": "USA-CO",
            "start": "2001Q1",
            "end": "2021Q4",
            "updated": "2022-02-25T15:25:17-0500",
            "data": [
                [
                    "2021Q4",
                    27.16702
                ],
                [
                    "2021Q3",
                    41.65969
                ],
                [
                    "2021Q2",
                    32.02714
                ],
                [
                    "2021Q1",
                    30.26405
                ],
                [
                    "2020Q4",
                    34.81531
                ],
                [
                    "2020Q3",
                    47.98452
                ],
                [
                    "2020Q2",
                    36.95866
                ],
                [
                    "2020Q1",
                    39.7883
                ],
                [
                    "2019Q4",
                    34.98954
                ],
                [
                    "2019Q3",
                    44.42765
                ],
                [
                    "2019Q2",
                    32.10459
                ],
                [
                    "2019Q1",
                    35.13722
                ],
                [
                    "2018Q4",
                    33.14312
                ],
                [
                    "2018Q3",
                    41.19529
                ],
                [
                    "2018Q2",
                    32.92753
                ],
                [
                    "2018Q1",
                    31.61529
                ],
                [
                    "2017Q4",
                    23.92098
                ],
                [
                    "2017Q3",
                    35.24108
                ],
                [
                    "2017Q2",
                    25.41658
                ],
                [
                    "2017Q1",
                    21.5799
                ],
                [
                    "2016Q4",
                    20.92805
                ],
                [
                    "2016Q3",
                    31.40782
                ],
                [
                    "2016Q2",
                    29.59389
                ],
                [
                    "2016Q1",
                    23.42645
                ],
                [
                    "2015Q4",
                    28.25592
                ],
                [
                    "2015Q3",
                    31.12047
                ],
                [
                    "2015Q2",
                    20.19739
                ],
                [
                    "2015Q1",
                    20.184
                ],
                [
                    "2014Q4",
                    28.99661
                ],
                [
                    "2014Q3",
                    28.8673
                ],
                [
                    "2014Q2",
                    22.46343
                ],
                [
                    "2014Q1",
                    22.00774
                ],
                [
                    "2013Q4",
                    21.18333
                ],
                [
                    "2013Q3",
                    30.7654
                ],
                [
                    "2013Q2",
                    22.81296
                ],
                [
                    "2013Q1",
                    19.69552
                ],
                [
                    "2012Q4",
                    16.85752
                ],
                [
                    "2012Q3",
                    30.53658
                ],
                [
                    "2012Q2",
                    23.55052
                ],
                [
                    "2012Q1",
                    19.49587
                ],
                [
                    "2011Q4",
                    21.83411
                ],
                [
                    "2011Q3",
                    24.75346
                ],
                [
                    "2011Q2",
                    22.48917
                ],
                [
                    "2011Q1",
                    19.31076
                ],
                [
                    "2010Q4",
                    20.70997
                ],
                [
                    "2010Q3",
                    27.60336
                ],
                [
                    "2010Q2",
                    22.18623
                ],
                [
                    "2010Q1",
                    25.01592
                ],
                [
                    "2009Q4",
                    26.53921
                ],
                [
                    "2009Q3",
                    33.4759
                ],
                [
                    "2009Q2",
                    28.6454
                ],
                [
                    "2009Q1",
                    30.95788
                ],
                [
                    "2008Q4",
                    29.14048
                ],
                [
                    "2008Q3",
                    33.37849
                ],
                [
                    "2008Q2",
                    23.18696
                ],
                [
                    "2008Q1",
                    25.80263
                ],
                [
                    "2007Q4",
                    34.09755
                ],
                [
                    "2007Q3",
                    40.47128
                ],
                [
                    "2007Q2",
                    30.09773
                ],
                [
                    "2007Q1",
                    25.15707
                ],
                [
                    "2006Q4",
                    27.2835
                ],
                [
                    "2006Q3",
                    27.79227
                ],
                [
                    "2006Q2",
                    21.96138
                ],
                [
                    "2006Q1",
                    24.94423
                ],
                [
                    "2005Q4",
                    25.55737
                ],
                [
                    "2005Q3",
                    31.09935
                ],
                [
                    "2005Q2",
                    22.33158
                ],
                [
                    "2005Q1",
                    22.21869
                ],
                [
                    "2004Q4",
                    26.42852
                ],
                [
                    "2004Q3",
                    26.94573
                ],
                [
                    "2004Q2",
                    21.1141
                ],
                [
                    "2004Q1",
                    18.35369
                ],
                [
                    "2003Q4",
                    20.469
                ],
                [
                    "2003Q3",
                    28.7
                ],
                [
                    "2003Q2",
                    16.9
                ],
                [
                    "2003Q1",
                    20.475
                ],
                [
                    "2002Q4",
                    20.66
                ],
                [
                    "2002Q3",
                    24.3
                ],
                [
                    "2002Q2",
                    21.128
                ],
                [
                    "2002Q1",
                    22.211
                ],
                [
                    "2001Q4",
                    22.859
                ],
                [
                    "2001Q3",
                    25.891
                ],
                [
                    "2001Q2",
                    24.154
                ],
                [
                    "2001Q1",
                    23.888
                ]
            ]
        }
    ]
}