{
    "request": {
        "command": "series",
        "series_id": "ELEC.CONS_TOT_BTU.COW-MS-99.Q"
    },
    "series": [
        {
            "series_id": "ELEC.CONS_TOT_BTU.COW-MS-99.Q",
            "name": "Total consumption (Btu) : coal : Mississippi : all sectors : quarterly",
            "units": "million MMBtu",
            "f": "Q",
            "description": "Summation of all types of coal; All sectors; ",
            "copyright": "None",
            "source": "EIA, U.S. Energy Information Administration",
            "iso3166": "USA-MS",
            "geography": "USA-MS",
            "start": "2001Q1",
            "end": "2021Q4",
            "updated": "2022-02-25T15:25:17-0500",
            "data": [
                [
                    "2021Q4",
                    13.2444
                ],
                [
                    "2021Q3",
                    15.64713
                ],
                [
                    "2021Q2",
                    15.81735
                ],
                [
                    "2021Q1",
                    17.54554
                ],
                [
                    "2020Q4",
                    9.42929
                ],
                [
                    "2020Q3",
                    19.09445
                ],
                [
                    "2020Q2",
                    12.52921
                ],
                [
                    "2020Q1",
                    10.88743
                ],
                [
                    "2019Q4",
                    6.29525
                ],
                [
                    "2019Q3",
                    16.78168
                ],
                [
                    "2019Q2",
                    17.34332
                ],
                [
                    "2019Q1",
                    10.04225
                ],
                [
                    "2018Q4",
                    16.34928
                ],
                [
                    "2018Q3",
                    16.13131
                ],
                [
                    "2018Q2",
                    16.32878
                ],
                [
                    "2018Q1",
                    11.20551
                ],
                [
                    "2017Q4",
                    12.7164
                ],
                [
                    "2017Q3",
                    14.15894
                ],
                [
                    "2017Q2",
                    13.98986
                ],
                [
                    "2017Q1",
                    12.91374
                ],
                [
                    "2016Q4",
                    13.73622
                ],
                [
                    "2016Q3",
                    21.59143
                ],
                [
                    "2016Q2",
                    11.06101
                ],
                [
                    "2016Q1",
                    14.82987
                ],
                [
                    "2015Q4",
                    7.79529
                ],
                [
                    "2015Q3",
                    23.12866
                ],
                [
                    "2015Q2",
                    18.09719
                ],
                [
                    "2015Q1",
                    20.04295
                ],
                [
                    "2014Q4",
                    17.44083
                ],
                [
                    "2014Q3",
                    35.90211
                ],
                [
                    "2014Q2",
                    31.81275
                ],
                [
                    "2014Q1",
                    28.86499
                ],
                [
                    "2013Q4",
                    21.00793
                ],
                [
                    "2013Q3",
                    30.39523
                ],
                [
                    "2013Q2",
                    24.50667
                ],
                [
                    "2013Q1",
                    19.05579
                ],
                [
                    "2012Q4",
                    15.62861
                ],
                [
                    "2012Q3",
                    27.69164
                ],
                [
                    "2012Q2",
                    20.53541
                ],
                [
                    "2012Q1",
                    15.99283
                ],
                [
                    "2011Q4",
                    19.4467
                ],
                [
                    "2011Q3",
                    32.86004
                ],
                [
                    "2011Q2",
                    30.16705
                ],
                [
                    "2011Q1",
                    22.45024
                ],
                [
                    "2010Q4",
                    31.69646
                ],
                [
                    "2010Q3",
                    45.14257
                ],
                [
                    "2010Q2",
                    34.86562
                ],
                [
                    "2010Q1",
                    33.90923
                ],
                [
                    "2009Q4",
                    33.97565
                ],
                [
                    "2009Q3",
                    42.2705
                ],
                [
                    "2009Q2",
                    34.90263
                ],
                [
                    "2009Q1",
                    28.01537
                ],
                [
                    "2008Q4",
                    32.86429
                ],
                [
                    "2008Q3",
                    47.97327
                ],
                [
                    "2008Q2",
                    48.84173
                ],
                [
                    "2008Q1",
                    44.5763
                ],
                [
                    "2007Q4",
                    39.15652
                ],
                [
                    "2007Q3",
                    49.36718
                ],
                [
                    "2007Q2",
                    47.65491
                ],
                [
                    "2007Q1",
                    45.43378
                ],
                [
                    "2006Q4",
                    51.21584
                ],
                [
                    "2006Q3",
                    51.817
                ],
                [
                    "2006Q2",
                    42.65007
                ],
                [
                    "2006Q1",
                    41.03016
                ],
                [
                    "2005Q4",
                    37.16984
                ],
                [
                    "2005Q3",
                    43.95384
                ],
                [
                    "2005Q2",
                    46.72179
                ],
                [
                    "2005Q1",
                    45.81721
                ],
                [
                    "2004Q4",
                    42.93467
                ],
                [
                    "2004Q3",
                    51.16955
                ],
                [
                    "2004Q2",
                    43.65255
                ],
                [
                    "2004Q1",
                    43.73423
                ],
                [
                    "2003Q4",
                    44.912
                ],
                [
                    "2003Q3",
                    50.088
                ],
                [
                    "2003Q2",
                    45.96
                ],
                [
                    "2003Q1",
                    35.221
                ],
                [
                    "2002Q4",
                    45.718
                ],
                [
                    "2002Q3",
                    46.094
                ],
                [
                    "2002Q2",
                    39.594
                ],
                [
                    "2002Q1",
                    19.301
                ],
                [
                    "2001Q4",
                    51.328
                ],
                [
                    "2001Q3",
                    50.103
                ],
                [
                    "2001Q2",
                    47.263
                ],
                [
                    "2001Q1",
                    45.859
                ]
            ]
        }
    ]
}