{
    "request": {
        "command": "series",
        "series_id": "ELEC.CONS_TOT_BTU.COW-AL-99.Q"
    },
    "series": [
        {
            "series_id": "ELEC.CONS_TOT_BTU.COW-AL-99.Q",
            "name": "Total consumption (Btu) : coal : Alabama : all sectors : quarterly",
            "units": "million MMBtu",
            "f": "Q",
            "description": "Summation of all types of coal; All sectors; ",
            "copyright": "None",
            "source": "EIA, U.S. Energy Information Administration",
            "iso3166": "USA-AL",
            "geography": "USA-AL",
            "start": "2001Q1",
            "end": "2021Q4",
            "updated": "2022-02-25T15:25:17-0500",
            "data": [
                [
                    "2021Q4",
                    64.13747
                ],
                [
                    "2021Q3",
                    82.89686
                ],
                [
                    "2021Q2",
                    54.94865
                ],
                [
                    "2021Q1",
                    68.71447
                ],
                [
                    "2020Q4",
                    58.64069
                ],
                [
                    "2020Q3",
                    72.01903
                ],
                [
                    "2020Q2",
                    42.48408
                ],
                [
                    "2020Q1",
                    46.80095
                ],
                [
                    "2019Q4",
                    65.65976
                ],
                [
                    "2019Q3",
                    75.90142
                ],
                [
                    "2019Q2",
                    56.98595
                ],
                [
                    "2019Q1",
                    70.78737
                ],
                [
                    "2018Q4",
                    60.5975
                ],
                [
                    "2018Q3",
                    94.91371
                ],
                [
                    "2018Q2",
                    80.12512
                ],
                [
                    "2018Q1",
                    84.24461
                ],
                [
                    "2017Q4",
                    73.1852
                ],
                [
                    "2017Q3",
                    91.58802
                ],
                [
                    "2017Q2",
                    77.45285
                ],
                [
                    "2017Q1",
                    75.90916
                ],
                [
                    "2016Q4",
                    86.06024
                ],
                [
                    "2016Q3",
                    111.74324
                ],
                [
                    "2016Q2",
                    76.55219
                ],
                [
                    "2016Q1",
                    75.07102
                ],
                [
                    "2015Q4",
                    85.75649
                ],
                [
                    "2015Q3",
                    138.99385
                ],
                [
                    "2015Q2",
                    112.01779
                ],
                [
                    "2015Q1",
                    93.19606
                ],
                [
                    "2014Q4",
                    98.44639
                ],
                [
                    "2014Q3",
                    142.77324
                ],
                [
                    "2014Q2",
                    125.37513
                ],
                [
                    "2014Q1",
                    129.12961
                ],
                [
                    "2013Q4",
                    119.96139
                ],
                [
                    "2013Q3",
                    141.96637
                ],
                [
                    "2013Q2",
                    127.29823
                ],
                [
                    "2013Q1",
                    110.04254
                ],
                [
                    "2012Q4",
                    124.26955
                ],
                [
                    "2012Q3",
                    156.86617
                ],
                [
                    "2012Q2",
                    115.67829
                ],
                [
                    "2012Q1",
                    87.38412
                ],
                [
                    "2011Q4",
                    117.94125
                ],
                [
                    "2011Q3",
                    171.0643
                ],
                [
                    "2011Q2",
                    153.01482
                ],
                [
                    "2011Q1",
                    154.97115
                ],
                [
                    "2010Q4",
                    141.38014
                ],
                [
                    "2010Q3",
                    181.30655
                ],
                [
                    "2010Q2",
                    173.89877
                ],
                [
                    "2010Q1",
                    165.16435
                ],
                [
                    "2009Q4",
                    134.82527
                ],
                [
                    "2009Q3",
                    159.60229
                ],
                [
                    "2009Q2",
                    132.88106
                ],
                [
                    "2009Q1",
                    156.39
                ],
                [
                    "2008Q4",
                    175.4842
                ],
                [
                    "2008Q3",
                    207.23229
                ],
                [
                    "2008Q2",
                    202.73815
                ],
                [
                    "2008Q1",
                    188.64739
                ],
                [
                    "2007Q4",
                    190.2598
                ],
                [
                    "2007Q3",
                    222.51244
                ],
                [
                    "2007Q2",
                    213.61337
                ],
                [
                    "2007Q1",
                    194.11786
                ],
                [
                    "2006Q4",
                    207.80447
                ],
                [
                    "2006Q3",
                    220.62342
                ],
                [
                    "2006Q2",
                    201.06672
                ],
                [
                    "2006Q1",
                    184.36942
                ],
                [
                    "2005Q4",
                    205.40997
                ],
                [
                    "2005Q3",
                    223.44611
                ],
                [
                    "2005Q2",
                    188.95504
                ],
                [
                    "2005Q1",
                    194.92655
                ],
                [
                    "2004Q4",
                    195.41149
                ],
                [
                    "2004Q3",
                    212.38041
                ],
                [
                    "2004Q2",
                    188.51617
                ],
                [
                    "2004Q1",
                    169.68729
                ],
                [
                    "2003Q4",
                    192.189
                ],
                [
                    "2003Q3",
                    225.231
                ],
                [
                    "2003Q2",
                    188.433
                ],
                [
                    "2003Q1",
                    182.861
                ],
                [
                    "2002Q4",
                    202.559
                ],
                [
                    "2002Q3",
                    225.51
                ],
                [
                    "2002Q2",
                    180.595
                ],
                [
                    "2002Q1",
                    155.087
                ],
                [
                    "2001Q4",
                    175.177
                ],
                [
                    "2001Q3",
                    217.758
                ],
                [
                    "2001Q2",
                    177.944
                ],
                [
                    "2001Q1",
                    188.385
                ]
            ]
        }
    ]
}