{
    "request": {
        "command": "series",
        "series_id": "ELEC.CONS_TOT_BTU.NG-TN-99.Q"
    },
    "series": [
        {
            "series_id": "ELEC.CONS_TOT_BTU.NG-TN-99.Q",
            "name": "Total consumption (Btu) : natural gas : Tennessee : all sectors : quarterly",
            "units": "million MMBtu",
            "f": "Q",
            "description": "Natural Gas; All sectors; ",
            "copyright": "None",
            "source": "EIA, U.S. Energy Information Administration",
            "iso3166": "USA-TN",
            "geography": "USA-TN",
            "start": "2001Q1",
            "end": "2021Q4",
            "updated": "2022-02-25T15:25:17-0500",
            "data": [
                [
                    "2021Q4",
                    27.84006
                ],
                [
                    "2021Q3",
                    43.87557
                ],
                [
                    "2021Q2",
                    30.2155
                ],
                [
                    "2021Q1",
                    35.03774
                ],
                [
                    "2020Q4",
                    33.99649
                ],
                [
                    "2020Q3",
                    40.34234
                ],
                [
                    "2020Q2",
                    30.64616
                ],
                [
                    "2020Q1",
                    38.06225
                ],
                [
                    "2019Q4",
                    35.14644
                ],
                [
                    "2019Q3",
                    45.08224
                ],
                [
                    "2019Q2",
                    34.80974
                ],
                [
                    "2019Q1",
                    38.89387
                ],
                [
                    "2018Q4",
                    32.39107
                ],
                [
                    "2018Q3",
                    41.09347
                ],
                [
                    "2018Q2",
                    25.87624
                ],
                [
                    "2018Q1",
                    28.60726
                ],
                [
                    "2017Q4",
                    23.14907
                ],
                [
                    "2017Q3",
                    27.34829
                ],
                [
                    "2017Q2",
                    22.07199
                ],
                [
                    "2017Q1",
                    24.99757
                ],
                [
                    "2016Q4",
                    23.23455
                ],
                [
                    "2016Q3",
                    34.0457
                ],
                [
                    "2016Q2",
                    24.41295
                ],
                [
                    "2016Q1",
                    22.90657
                ],
                [
                    "2015Q4",
                    19.59613
                ],
                [
                    "2015Q3",
                    23.09658
                ],
                [
                    "2015Q2",
                    20.9947
                ],
                [
                    "2015Q1",
                    19.10332
                ],
                [
                    "2014Q4",
                    12.03867
                ],
                [
                    "2014Q3",
                    15.94944
                ],
                [
                    "2014Q2",
                    14.30262
                ],
                [
                    "2014Q1",
                    10.68249
                ],
                [
                    "2013Q4",
                    9.57937
                ],
                [
                    "2013Q3",
                    11.92789
                ],
                [
                    "2013Q2",
                    6.17321
                ],
                [
                    "2013Q1",
                    14.88993
                ],
                [
                    "2012Q4",
                    14.66888
                ],
                [
                    "2012Q3",
                    22.96919
                ],
                [
                    "2012Q2",
                    20.02435
                ],
                [
                    "2012Q1",
                    10.56454
                ],
                [
                    "2011Q4",
                    6.56514
                ],
                [
                    "2011Q3",
                    8.8747
                ],
                [
                    "2011Q2",
                    11.40202
                ],
                [
                    "2011Q1",
                    4.24493
                ],
                [
                    "2010Q4",
                    8.72675
                ],
                [
                    "2010Q3",
                    10.91822
                ],
                [
                    "2010Q2",
                    3.89618
                ],
                [
                    "2010Q1",
                    2.1697
                ],
                [
                    "2009Q4",
                    1.28129
                ],
                [
                    "2009Q3",
                    1.48944
                ],
                [
                    "2009Q2",
                    1.93733
                ],
                [
                    "2009Q1",
                    1.63686
                ],
                [
                    "2008Q4",
                    0.9322
                ],
                [
                    "2008Q3",
                    2.50844
                ],
                [
                    "2008Q2",
                    1.50478
                ],
                [
                    "2008Q1",
                    1.90899
                ],
                [
                    "2007Q4",
                    1.75174
                ],
                [
                    "2007Q3",
                    6.06439
                ],
                [
                    "2007Q2",
                    1.22664
                ],
                [
                    "2007Q1",
                    1.5973
                ],
                [
                    "2006Q4",
                    1.72838
                ],
                [
                    "2006Q3",
                    5.72572
                ],
                [
                    "2006Q2",
                    2.23904
                ],
                [
                    "2006Q1",
                    0.98253
                ],
                [
                    "2005Q4",
                    0.90114
                ],
                [
                    "2005Q3",
                    5.1382
                ],
                [
                    "2005Q2",
                    1.36364
                ],
                [
                    "2005Q1",
                    1.02287
                ],
                [
                    "2004Q4",
                    1.1607
                ],
                [
                    "2004Q3",
                    1.42499
                ],
                [
                    "2004Q2",
                    1.80231
                ],
                [
                    "2004Q1",
                    1.67196
                ],
                [
                    "2003Q4",
                    1.583
                ],
                [
                    "2003Q3",
                    3.237
                ],
                [
                    "2003Q2",
                    2.351
                ],
                [
                    "2003Q1",
                    3.645
                ],
                [
                    "2002Q4",
                    2.298
                ],
                [
                    "2002Q3",
                    3.249
                ],
                [
                    "2002Q2",
                    2.174
                ],
                [
                    "2002Q1",
                    1.863
                ],
                [
                    "2001Q4",
                    2.057
                ],
                [
                    "2001Q3",
                    4.674
                ],
                [
                    "2001Q2",
                    2.381
                ],
                [
                    "2001Q1",
                    1.581
                ]
            ]
        }
    ]
}