{
    "request": {
        "command": "series",
        "series_id": "ELEC.GEN.HYC-US-99.Q"
    },
    "series": [
        {
            "series_id": "ELEC.GEN.HYC-US-99.Q",
            "name": "Net generation : conventional hydroelectric : United States : all sectors : quarterly",
            "units": "thousand megawatthours",
            "f": "Q",
            "description": "Hydroelectric powered dams other than reversible pumped storage; All sectors; ",
            "copyright": "None",
            "source": "EIA, U.S. Energy Information Administration",
            "iso3166": "USA",
            "geography": "USA",
            "start": "2001Q1",
            "end": "2021Q4",
            "updated": "2022-02-25T15:25:17-0500",
            "data": [
                [
                    "2021Q4",
                    64108.53265
                ],
                [
                    "2021Q3",
                    61033.80223
                ],
                [
                    "2021Q2",
                    66071.23028
                ],
                [
                    "2021Q1",
                    69011.32019
                ],
                [
                    "2020Q4",
                    61210.91245
                ],
                [
                    "2020Q3",
                    68704.14708
                ],
                [
                    "2020Q2",
                    81169.89887
                ],
                [
                    "2020Q1",
                    74188.93643
                ],
                [
                    "2019Q4",
                    60001.5916
                ],
                [
                    "2019Q3",
                    65979.82595
                ],
                [
                    "2019Q2",
                    87879.98143
                ],
                [
                    "2019Q1",
                    74012.33153
                ],
                [
                    "2018Q4",
                    64258.06866
                ],
                [
                    "2018Q3",
                    66282.05512
                ],
                [
                    "2018Q2",
                    86156.92684
                ],
                [
                    "2018Q1",
                    75826.93821
                ],
                [
                    "2017Q4",
                    59834.35511
                ],
                [
                    "2017Q3",
                    67783.85763
                ],
                [
                    "2017Q2",
                    92591.87636
                ],
                [
                    "2017Q1",
                    80122.84056
                ],
                [
                    "2016Q4",
                    58674.88638
                ],
                [
                    "2016Q3",
                    57392.5541
                ],
                [
                    "2016Q2",
                    74601.2776
                ],
                [
                    "2016Q1",
                    77143.43501
                ],
                [
                    "2015Q4",
                    59133.79438
                ],
                [
                    "2015Q3",
                    56230.44895
                ],
                [
                    "2015Q2",
                    63010.47683
                ],
                [
                    "2015Q1",
                    70705.36467
                ],
                [
                    "2014Q4",
                    58112.92383
                ],
                [
                    "2014Q3",
                    60238.9758
                ],
                [
                    "2014Q2",
                    77727.66939
                ],
                [
                    "2014Q1",
                    63287.05285
                ],
                [
                    "2013Q4",
                    56003.72716
                ],
                [
                    "2013Q3",
                    65849.03941
                ],
                [
                    "2013Q2",
                    80931.26541
                ],
                [
                    "2013Q1",
                    65781.35075
                ],
                [
                    "2012Q4",
                    58219.36806
                ],
                [
                    "2012Q3",
                    67128.73579
                ],
                [
                    "2012Q2",
                    81594.37288
                ],
                [
                    "2012Q1",
                    69297.74257
                ],
                [
                    "2011Q4",
                    64199.86075
                ],
                [
                    "2011Q3",
                    78425.80452
                ],
                [
                    "2011Q2",
                    95932.44692
                ],
                [
                    "2011Q1",
                    80796.79126
                ],
                [
                    "2010Q4",
                    60413.59783
                ],
                [
                    "2010Q3",
                    61901.19997
                ],
                [
                    "2010Q2",
                    74029.70647
                ],
                [
                    "2010Q1",
                    63858.56512
                ],
                [
                    "2009Q4",
                    65428.57749
                ],
                [
                    "2009Q3",
                    60323.87864
                ],
                [
                    "2009Q2",
                    84562.85708
                ],
                [
                    "2009Q1",
                    63129.78097
                ],
                [
                    "2008Q4",
                    51999.36709
                ],
                [
                    "2008Q3",
                    62962.55608
                ],
                [
                    "2008Q2",
                    78632.50659
                ],
                [
                    "2008Q1",
                    61236.95535
                ],
                [
                    "2007Q4",
                    48820.16127
                ],
                [
                    "2007Q3",
                    57160.84575
                ],
                [
                    "2007Q2",
                    72754.16756
                ],
                [
                    "2007Q1",
                    68774.79973
                ],
                [
                    "2006Q4",
                    58922.85078
                ],
                [
                    "2006Q3",
                    64369.20693
                ],
                [
                    "2006Q2",
                    89131.41
                ],
                [
                    "2006Q1",
                    76822.94796
                ],
                [
                    "2005Q4",
                    59500.1848
                ],
                [
                    "2005Q3",
                    64886.20435
                ],
                [
                    "2005Q2",
                    77119.85952
                ],
                [
                    "2005Q1",
                    68815.00628
                ],
                [
                    "2004Q4",
                    66010.55827
                ],
                [
                    "2004Q3",
                    65435.50832
                ],
                [
                    "2004Q2",
                    70160.03796
                ],
                [
                    "2004Q1",
                    66811.20382
                ],
                [
                    "2003Q4",
                    62188.018
                ],
                [
                    "2003Q3",
                    66295.58
                ],
                [
                    "2003Q2",
                    82740.518
                ],
                [
                    "2003Q1",
                    64582.212
                ],
                [
                    "2002Q4",
                    58569.903
                ],
                [
                    "2002Q3",
                    63641.353
                ],
                [
                    "2002Q2",
                    79122.147
                ],
                [
                    "2002Q1",
                    62995.428
                ],
                [
                    "2001Q4",
                    49993.746
                ],
                [
                    "2001Q3",
                    52248.914
                ],
                [
                    "2001Q2",
                    57916.259
                ],
                [
                    "2001Q1",
                    56802.126
                ]
            ]
        }
    ]
}