{
    "request": {
        "command": "series",
        "series_id": "ELEC.GEN.AOR-US-99.Q"
    },
    "series": [
        {
            "series_id": "ELEC.GEN.AOR-US-99.Q",
            "name": "Net generation : other renewables (total) : United States : all sectors : quarterly",
            "units": "thousand megawatthours",
            "f": "Q",
            "description": "Summation of all renewable sources including wind, solar, biomass, geothermal and other renewable sources other than hydroelectric dams; All sectors; ",
            "copyright": "None",
            "source": "EIA, U.S. Energy Information Administration",
            "iso3166": "USA",
            "geography": "USA",
            "start": "2001Q1",
            "end": "2021Q4",
            "updated": "2022-02-25T15:25:17-0500",
            "data": [
                [
                    "2021Q4",
                    150331.4021
                ],
                [
                    "2021Q3",
                    130219.87883
                ],
                [
                    "2021Q2",
                    148940.83311
                ],
                [
                    "2021Q1",
                    136670.36244
                ],
                [
                    "2020Q4",
                    129425.38977
                ],
                [
                    "2020Q3",
                    114340.32656
                ],
                [
                    "2020Q2",
                    132773.80021
                ],
                [
                    "2020Q1",
                    121189.95401
                ],
                [
                    "2019Q4",
                    110957.66351
                ],
                [
                    "2019Q3",
                    108584.82868
                ],
                [
                    "2019Q2",
                    116621.25659
                ],
                [
                    "2019Q1",
                    104635.2272
                ],
                [
                    "2018Q4",
                    98538.56244
                ],
                [
                    "2018Q3",
                    94045.42327
                ],
                [
                    "2018Q2",
                    114379.22653
                ],
                [
                    "2018Q1",
                    107328.6136
                ],
                [
                    "2017Q4",
                    99868.949
                ],
                [
                    "2017Q3",
                    84071.33816
                ],
                [
                    "2017Q2",
                    104481.08845
                ],
                [
                    "2017Q1",
                    97828.37102
                ],
                [
                    "2016Q4",
                    91150.94767
                ],
                [
                    "2016Q3",
                    79367.17207
                ],
                [
                    "2016Q2",
                    84613.86628
                ],
                [
                    "2016Q1",
                    86500.96229
                ],
                [
                    "2015Q4",
                    81374.74628
                ],
                [
                    "2015Q3",
                    68923.2693
                ],
                [
                    "2015Q2",
                    75237.21424
                ],
                [
                    "2015Q1",
                    69625.6739
                ],
                [
                    "2014Q4",
                    72147.38419
                ],
                [
                    "2014Q3",
                    59958.35083
                ],
                [
                    "2014Q2",
                    74762.24072
                ],
                [
                    "2014Q1",
                    72344.72225
                ],
                [
                    "2013Q4",
                    65713.89335
                ],
                [
                    "2013Q3",
                    54966.02838
                ],
                [
                    "2013Q2",
                    68169.33912
                ],
                [
                    "2013Q1",
                    64658.80555
                ],
                [
                    "2012Q4",
                    58842.98244
                ],
                [
                    "2012Q3",
                    46458.31336
                ],
                [
                    "2012Q2",
                    55930.53709
                ],
                [
                    "2012Q1",
                    57101.14843
                ],
                [
                    "2011Q4",
                    52324.54428
                ],
                [
                    "2011Q3",
                    41101.8304
                ],
                [
                    "2011Q2",
                    53047.25354
                ],
                [
                    "2011Q1",
                    47507.56405
                ],
                [
                    "2010Q4",
                    44931.99865
                ],
                [
                    "2010Q3",
                    39434.62357
                ],
                [
                    "2010Q2",
                    44447.27179
                ],
                [
                    "2010Q1",
                    38359.11306
                ],
                [
                    "2009Q4",
                    38538.81233
                ],
                [
                    "2009Q3",
                    33502.44266
                ],
                [
                    "2009Q2",
                    36317.87344
                ],
                [
                    "2009Q1",
                    35919.57487
                ],
                [
                    "2008Q4",
                    33819.61925
                ],
                [
                    "2008Q3",
                    28771.10906
                ],
                [
                    "2008Q2",
                    33215.66698
                ],
                [
                    "2008Q1",
                    30294.60777
                ],
                [
                    "2007Q4",
                    27943.11044
                ],
                [
                    "2007Q3",
                    26108.54565
                ],
                [
                    "2007Q2",
                    25862.91869
                ],
                [
                    "2007Q1",
                    25322.9366
                ],
                [
                    "2006Q4",
                    25103.58741
                ],
                [
                    "2006Q3",
                    23735.78125
                ],
                [
                    "2006Q2",
                    23678.06872
                ],
                [
                    "2006Q1",
                    24008.05527
                ],
                [
                    "2005Q4",
                    22260.16257
                ],
                [
                    "2005Q3",
                    22094.646
                ],
                [
                    "2005Q2",
                    22380.82529
                ],
                [
                    "2005Q1",
                    20593.76436
                ],
                [
                    "2004Q4",
                    20366.79277
                ],
                [
                    "2004Q3",
                    20990.25817
                ],
                [
                    "2004Q2",
                    21332.76949
                ],
                [
                    "2004Q1",
                    20377.50294
                ],
                [
                    "2003Q4",
                    20145.39782
                ],
                [
                    "2003Q3",
                    20336.08849
                ],
                [
                    "2003Q2",
                    19824.51476
                ],
                [
                    "2003Q1",
                    19180.79028
                ],
                [
                    "2002Q4",
                    19305.73476
                ],
                [
                    "2002Q3",
                    20682.39978
                ],
                [
                    "2002Q2",
                    20368.23034
                ],
                [
                    "2002Q1",
                    18752.80754
                ],
                [
                    "2001Q4",
                    17801.51397
                ],
                [
                    "2001Q3",
                    18307.40893
                ],
                [
                    "2001Q2",
                    17529.23009
                ],
                [
                    "2001Q1",
                    17130.49098
                ]
            ]
        }
    ]
}