{
    "request": {
        "command": "series",
        "series_id": "ELEC.GEN.HYC-CT-99.Q"
    },
    "series": [
        {
            "series_id": "ELEC.GEN.HYC-CT-99.Q",
            "name": "Net generation : conventional hydroelectric : Connecticut : all sectors : quarterly",
            "units": "thousand megawatthours",
            "f": "Q",
            "description": "Hydroelectric powered dams other than reversible pumped storage; All sectors; ",
            "copyright": "None",
            "source": "EIA, U.S. Energy Information Administration",
            "iso3166": "USA-CT",
            "geography": "USA-CT",
            "start": "2001Q1",
            "end": "2021Q4",
            "updated": "2022-02-25T15:25:17-0500",
            "data": [
                [
                    "2021Q4",
                    79.05441
                ],
                [
                    "2021Q3",
                    81.00653
                ],
                [
                    "2021Q2",
                    77.79656
                ],
                [
                    "2021Q1",
                    85.83733
                ],
                [
                    "2020Q4",
                    76.87599
                ],
                [
                    "2020Q3",
                    31.08955
                ],
                [
                    "2020Q2",
                    103.5347
                ],
                [
                    "2020Q1",
                    114.44391
                ],
                [
                    "2019Q4",
                    96.02962
                ],
                [
                    "2019Q3",
                    45.36991
                ],
                [
                    "2019Q2",
                    144.53086
                ],
                [
                    "2019Q1",
                    141.9869
                ],
                [
                    "2018Q4",
                    170.2039
                ],
                [
                    "2018Q3",
                    82.32535
                ],
                [
                    "2018Q2",
                    147.14579
                ],
                [
                    "2018Q1",
                    155.64413
                ],
                [
                    "2017Q4",
                    67.16833
                ],
                [
                    "2017Q3",
                    59.4473
                ],
                [
                    "2017Q2",
                    124.32919
                ],
                [
                    "2017Q1",
                    81.24199
                ],
                [
                    "2016Q4",
                    44.29664
                ],
                [
                    "2016Q3",
                    35.73089
                ],
                [
                    "2016Q2",
                    64.1472
                ],
                [
                    "2016Q1",
                    79.97017
                ],
                [
                    "2015Q4",
                    70.33565
                ],
                [
                    "2015Q3",
                    56.1474
                ],
                [
                    "2015Q2",
                    100.92132
                ],
                [
                    "2015Q1",
                    75.06268
                ],
                [
                    "2014Q4",
                    96.37349
                ],
                [
                    "2014Q3",
                    90.46545
                ],
                [
                    "2014Q2",
                    145.84121
                ],
                [
                    "2014Q1",
                    101.28007
                ],
                [
                    "2013Q4",
                    79.8082
                ],
                [
                    "2013Q3",
                    90.43827
                ],
                [
                    "2013Q2",
                    127.09422
                ],
                [
                    "2013Q1",
                    104.58736
                ],
                [
                    "2012Q4",
                    80.99298
                ],
                [
                    "2012Q3",
                    54.35639
                ],
                [
                    "2012Q2",
                    88.88209
                ],
                [
                    "2012Q1",
                    87.90956
                ],
                [
                    "2011Q4",
                    142.8126
                ],
                [
                    "2011Q3",
                    104.70293
                ],
                [
                    "2011Q2",
                    182.10955
                ],
                [
                    "2011Q1",
                    137.81694
                ],
                [
                    "2010Q4",
                    113.81073
                ],
                [
                    "2010Q3",
                    59.82561
                ],
                [
                    "2010Q2",
                    108.24225
                ],
                [
                    "2010Q1",
                    108.78871
                ],
                [
                    "2009Q4",
                    117.65925
                ],
                [
                    "2009Q3",
                    119.76696
                ],
                [
                    "2009Q2",
                    141.04264
                ],
                [
                    "2009Q1",
                    131.07674
                ],
                [
                    "2008Q4",
                    126.60885
                ],
                [
                    "2008Q3",
                    134.74857
                ],
                [
                    "2008Q2",
                    154.54518
                ],
                [
                    "2008Q1",
                    140.27468
                ],
                [
                    "2007Q4",
                    95.69822
                ],
                [
                    "2007Q3",
                    59.02152
                ],
                [
                    "2007Q2",
                    116.6839
                ],
                [
                    "2007Q1",
                    91.85715
                ],
                [
                    "2006Q4",
                    115.55293
                ],
                [
                    "2006Q3",
                    142.94263
                ],
                [
                    "2006Q2",
                    149.2441
                ],
                [
                    "2006Q1",
                    136.15234
                ],
                [
                    "2005Q4",
                    109.76304
                ],
                [
                    "2005Q3",
                    111.92269
                ],
                [
                    "2005Q2",
                    123.46704
                ],
                [
                    "2005Q1",
                    133.04622
                ],
                [
                    "2004Q4",
                    1.6738
                ],
                [
                    "2004Q3",
                    114.37991
                ],
                [
                    "2004Q2",
                    57.92542
                ],
                [
                    "2004Q1",
                    288.63312
                ],
                [
                    "2003Q4",
                    180.813
                ],
                [
                    "2003Q3",
                    96.865
                ],
                [
                    "2003Q2",
                    151.308
                ],
                [
                    "2003Q1",
                    135.431
                ],
                [
                    "2002Q4",
                    114.616
                ],
                [
                    "2002Q3",
                    27.989
                ],
                [
                    "2002Q2",
                    117.774
                ],
                [
                    "2002Q1",
                    74.709
                ],
                [
                    "2001Q4",
                    24.25
                ],
                [
                    "2001Q3",
                    31.745
                ],
                [
                    "2001Q2",
                    126.132
                ],
                [
                    "2001Q1",
                    104.246
                ]
            ]
        }
    ]
}