{
    "request": {
        "command": "series",
        "series_id": "ELEC.CONS_TOT_BTU.COW-MT-99.Q"
    },
    "series": [
        {
            "series_id": "ELEC.CONS_TOT_BTU.COW-MT-99.Q",
            "name": "Total consumption (Btu) : coal : Montana : all sectors : quarterly",
            "units": "million MMBtu",
            "f": "Q",
            "description": "Summation of all types of coal; All sectors; ",
            "copyright": "None",
            "source": "EIA, U.S. Energy Information Administration",
            "iso3166": "USA-MT",
            "geography": "USA-MT",
            "start": "2001Q1",
            "end": "2021Q4",
            "updated": "2022-02-25T15:25:17-0500",
            "data": [
                [
                    "2021Q4",
                    32.71911
                ],
                [
                    "2021Q3",
                    31.4941
                ],
                [
                    "2021Q2",
                    17.9125
                ],
                [
                    "2021Q1",
                    33.03054
                ],
                [
                    "2020Q4",
                    22.69815
                ],
                [
                    "2020Q3",
                    25.27932
                ],
                [
                    "2020Q2",
                    17.70342
                ],
                [
                    "2020Q1",
                    31.30706
                ],
                [
                    "2019Q4",
                    40.65497
                ],
                [
                    "2019Q3",
                    45.96784
                ],
                [
                    "2019Q2",
                    23.84123
                ],
                [
                    "2019Q1",
                    46.66761
                ],
                [
                    "2018Q4",
                    47.89731
                ],
                [
                    "2018Q3",
                    33.6588
                ],
                [
                    "2018Q2",
                    24.41458
                ],
                [
                    "2018Q1",
                    43.94585
                ],
                [
                    "2017Q4",
                    43.80282
                ],
                [
                    "2017Q3",
                    44.70556
                ],
                [
                    "2017Q2",
                    24.60711
                ],
                [
                    "2017Q1",
                    39.19933
                ],
                [
                    "2016Q4",
                    44.37619
                ],
                [
                    "2016Q3",
                    48.96984
                ],
                [
                    "2016Q2",
                    24.18497
                ],
                [
                    "2016Q1",
                    40.37765
                ],
                [
                    "2015Q4",
                    46.76526
                ],
                [
                    "2015Q3",
                    48.50485
                ],
                [
                    "2015Q2",
                    38.12033
                ],
                [
                    "2015Q1",
                    40.68612
                ],
                [
                    "2014Q4",
                    49.17636
                ],
                [
                    "2014Q3",
                    50.81989
                ],
                [
                    "2014Q2",
                    28.2225
                ],
                [
                    "2014Q1",
                    42.88531
                ],
                [
                    "2013Q4",
                    37.28675
                ],
                [
                    "2013Q3",
                    37.32225
                ],
                [
                    "2013Q2",
                    35.68958
                ],
                [
                    "2013Q1",
                    52.0906
                ],
                [
                    "2012Q4",
                    51.21229
                ],
                [
                    "2012Q3",
                    42.04852
                ],
                [
                    "2012Q2",
                    16.01144
                ],
                [
                    "2012Q1",
                    44.43584
                ],
                [
                    "2011Q4",
                    53.2816
                ],
                [
                    "2011Q3",
                    46.16917
                ],
                [
                    "2011Q2",
                    20.26742
                ],
                [
                    "2011Q1",
                    44.83032
                ],
                [
                    "2010Q4",
                    51.58904
                ],
                [
                    "2010Q3",
                    54.00268
                ],
                [
                    "2010Q2",
                    42.8499
                ],
                [
                    "2010Q1",
                    53.60266
                ],
                [
                    "2009Q4",
                    49.1717
                ],
                [
                    "2009Q3",
                    39.25884
                ],
                [
                    "2009Q2",
                    29.13128
                ],
                [
                    "2009Q1",
                    54.12226
                ],
                [
                    "2008Q4",
                    54.87679
                ],
                [
                    "2008Q3",
                    50.30282
                ],
                [
                    "2008Q2",
                    41.32019
                ],
                [
                    "2008Q1",
                    55.09171
                ],
                [
                    "2007Q4",
                    52.88671
                ],
                [
                    "2007Q3",
                    54.31205
                ],
                [
                    "2007Q2",
                    42.08379
                ],
                [
                    "2007Q1",
                    51.53373
                ],
                [
                    "2006Q4",
                    51.34325
                ],
                [
                    "2006Q3",
                    51.88485
                ],
                [
                    "2006Q2",
                    37.43119
                ],
                [
                    "2006Q1",
                    49.82646
                ],
                [
                    "2005Q4",
                    50.34686
                ],
                [
                    "2005Q3",
                    50.85606
                ],
                [
                    "2005Q2",
                    46.19157
                ],
                [
                    "2005Q1",
                    48.1565
                ],
                [
                    "2004Q4",
                    53.27142
                ],
                [
                    "2004Q3",
                    48.44038
                ],
                [
                    "2004Q2",
                    37.89287
                ],
                [
                    "2004Q1",
                    52.68448
                ],
                [
                    "2003Q4",
                    51.102
                ],
                [
                    "2003Q3",
                    50.948
                ],
                [
                    "2003Q2",
                    38.141
                ],
                [
                    "2003Q1",
                    47.389
                ],
                [
                    "2002Q4",
                    42.011
                ],
                [
                    "2002Q3",
                    43.523
                ],
                [
                    "2002Q2",
                    36.105
                ],
                [
                    "2002Q1",
                    43.283
                ],
                [
                    "2001Q4",
                    50.062
                ],
                [
                    "2001Q3",
                    50.515
                ],
                [
                    "2001Q2",
                    34.167
                ],
                [
                    "2001Q1",
                    46.987
                ]
            ]
        }
    ]
}