{
    "request": {
        "command": "series",
        "series_id": "ELEC.GEN.NG-TX-99.Q"
    },
    "series": [
        {
            "series_id": "ELEC.GEN.NG-TX-99.Q",
            "name": "Net generation : natural gas : Texas : all sectors : quarterly",
            "units": "thousand megawatthours",
            "f": "Q",
            "description": "Natural Gas; All sectors; ",
            "copyright": "None",
            "source": "EIA, U.S. Energy Information Administration",
            "iso3166": "USA-TX",
            "geography": "USA-TX",
            "start": "2001Q1",
            "end": "2021Q4",
            "updated": "2022-02-25T15:25:17-0500",
            "data": [
                [
                    "2021Q4",
                    52132.80486
                ],
                [
                    "2021Q3",
                    76466.61772
                ],
                [
                    "2021Q2",
                    57950.83606
                ],
                [
                    "2021Q1",
                    48391.67778
                ],
                [
                    "2020Q4",
                    51190.90099
                ],
                [
                    "2020Q3",
                    79520.40765
                ],
                [
                    "2020Q2",
                    59252.631
                ],
                [
                    "2020Q1",
                    56665.55154
                ],
                [
                    "2019Q4",
                    57939.90445
                ],
                [
                    "2019Q3",
                    85511.39084
                ],
                [
                    "2019Q2",
                    60358.17279
                ],
                [
                    "2019Q1",
                    51820.55257
                ],
                [
                    "2018Q4",
                    51916.17071
                ],
                [
                    "2018Q3",
                    77709.28573
                ],
                [
                    "2018Q2",
                    59382.63525
                ],
                [
                    "2018Q1",
                    50704.99221
                ],
                [
                    "2017Q4",
                    45711.78052
                ],
                [
                    "2017Q3",
                    68081.59691
                ],
                [
                    "2017Q2",
                    51122.4595
                ],
                [
                    "2017Q1",
                    39596.15874
                ],
                [
                    "2016Q4",
                    45085.40143
                ],
                [
                    "2016Q3",
                    69988.77802
                ],
                [
                    "2016Q2",
                    58166.19113
                ],
                [
                    "2016Q1",
                    52735.88966
                ],
                [
                    "2015Q4",
                    53706.19671
                ],
                [
                    "2015Q3",
                    72509.52531
                ],
                [
                    "2015Q2",
                    56483.23708
                ],
                [
                    "2015Q1",
                    55032.46825
                ],
                [
                    "2014Q4",
                    47988.19825
                ],
                [
                    "2014Q3",
                    64779.22294
                ],
                [
                    "2014Q2",
                    48817.58767
                ],
                [
                    "2014Q1",
                    43136.14584
                ],
                [
                    "2013Q4",
                    47723.4902
                ],
                [
                    "2013Q3",
                    65025.61186
                ],
                [
                    "2013Q2",
                    49235.83324
                ],
                [
                    "2013Q1",
                    41813.48028
                ],
                [
                    "2012Q4",
                    42232.13901
                ],
                [
                    "2012Q3",
                    66076.93436
                ],
                [
                    "2012Q2",
                    59096.19013
                ],
                [
                    "2012Q1",
                    46496.0183
                ],
                [
                    "2011Q4",
                    42838.66723
                ],
                [
                    "2011Q3",
                    69566.98241
                ],
                [
                    "2011Q2",
                    50335.77826
                ],
                [
                    "2011Q1",
                    37758.72103
                ],
                [
                    "2010Q4",
                    36732.25538
                ],
                [
                    "2010Q3",
                    61273.09982
                ],
                [
                    "2010Q2",
                    48543.07027
                ],
                [
                    "2010Q1",
                    40333.81216
                ],
                [
                    "2009Q4",
                    39279.09493
                ],
                [
                    "2009Q3",
                    64513.57504
                ],
                [
                    "2009Q2",
                    48852.23441
                ],
                [
                    "2009Q1",
                    36421.57849
                ],
                [
                    "2008Q4",
                    37900.61808
                ],
                [
                    "2008Q3",
                    60280.86015
                ],
                [
                    "2008Q2",
                    52494.62066
                ],
                [
                    "2008Q1",
                    42570.97882
                ],
                [
                    "2007Q4",
                    42720.25638
                ],
                [
                    "2007Q3",
                    63142.2849
                ],
                [
                    "2007Q2",
                    48654.11783
                ],
                [
                    "2007Q1",
                    45014.62184
                ],
                [
                    "2006Q4",
                    41054.57573
                ],
                [
                    "2006Q3",
                    65453.58393
                ],
                [
                    "2006Q2",
                    54274.00078
                ],
                [
                    "2006Q1",
                    37088.07286
                ],
                [
                    "2005Q4",
                    42301.13394
                ],
                [
                    "2005Q3",
                    65900.04852
                ],
                [
                    "2005Q2",
                    50823.75796
                ],
                [
                    "2005Q1",
                    38640.31799
                ],
                [
                    "2004Q4",
                    42553.71349
                ],
                [
                    "2004Q3",
                    59134.21078
                ],
                [
                    "2004Q2",
                    48257.46975
                ],
                [
                    "2004Q1",
                    38809.26905
                ],
                [
                    "2003Q4",
                    36998.128
                ],
                [
                    "2003Q3",
                    58772.211
                ],
                [
                    "2003Q2",
                    48205.199
                ],
                [
                    "2003Q1",
                    40935.812
                ],
                [
                    "2002Q4",
                    42939.42
                ],
                [
                    "2002Q3",
                    62705.106
                ],
                [
                    "2002Q2",
                    50271.33
                ],
                [
                    "2002Q1",
                    40517.552
                ],
                [
                    "2001Q4",
                    40489.096
                ],
                [
                    "2001Q3",
                    62298.46
                ],
                [
                    "2001Q2",
                    48748.711
                ],
                [
                    "2001Q1",
                    38574.715
                ]
            ]
        }
    ]
}